<Appendix name="External Code Sets"
		  xmlns:xs="http://www.w3.org/2001/XMLSchema"
		  xmlns:xhtml="http://www.w3.org/1999/xhtml"
		  xmlns:xsi="http://www.w3.org/2001/XMLSchema-instance"
		  
		  xmlns="http://sifassociation.org/SpecGen">
      
  <Intro>
    <p>
      All code sets defined by external bodies and referenced within SIF are included here for reference.  The left column in each table contains the individual code values that are used
      in SIF elements and attributes that reference these code sets.  These sets of code values are closed and normative for a given version of this specification.  Including
      codes not provided here in corresponding SIF elements and attributes can lead to XML validation errors in installations where the zone integration server or any agent
      is validating XML messages; the SIF data model allows for locally-defined codes, where deemed appropriate, in the <a href="DataModel.html#OtherCodeList">
        <code>OtherCodeList</code>
      </a>
      element.  The right column of each table may provide a textual equivalent or description of the corresponding code, and is provided for informational purposes only.
      The referenced sources for these code sets serve as the authorities for all descriptions and semantics, and for the definition and maintenance of the code set values themselves.
      In each release of this specification the SIF Association endeavors to synchronize referenced code sets with updates from external sources.
    </p>
  </Intro>
  <CodeSets>

<Grouping
 	xmlns="http://sifassociation.org/SpecGen"
	code="ISO" name="International Standards Organization (ISO)">


	<CodeSet>
		<Intro>
			<p>A country is a geopolitical entity recognised by the
			New Zealand government. The term country may include</p>
			<ul>
				<li>Independent countries recognised by the New Zealand
				Government</li>
				<li>Units that are recognised geographic areas</li>
				<li>administrative subdivisions of the United Kingdom</li>
				<li>overseas dependencies, external territories of independent
				countries.</li>
			</ul>
			<p>Conforms to the International Standard <a href="http://www.iso.org/iso/home/store/catalogue_ics/catalogue_detail_ics.htm?csnumber=63545">ISO 3166 Codes
			for the Representation of Names of Countries and their
			Subdivisions (ISO 3166-1:2013).</a>  Education adopts the
			alpha-3 representation of this standard. </p>
		</Intro>
		<ID>3166 Country</ID>
    <Values>
			<Value><Code>ABW</Code><Text>Aruba</Text></Value>
			<Value><Code>AFG</Code><Text>Afghanistan</Text></Value>
			<Value><Code>AGO</Code><Text>Angola</Text></Value>
			<Value><Code>AIA</Code><Text>Anguilla</Text></Value>
			<Value><Code>ALA</Code><Text>Åland Islands</Text></Value>
			<Value><Code>ALB</Code><Text>Albania</Text></Value>
			<Value><Code>AND</Code><Text>Andorra</Text></Value>
			<Value><Code>ARE</Code><Text>United Arab Emirates</Text></Value>
			<Value><Code>ARG</Code><Text>Argentina</Text></Value>
			<Value><Code>ARM</Code><Text>Armenia</Text></Value>
			<Value><Code>ASM</Code><Text>American Samoa</Text></Value>
			<Value><Code>ATA</Code><Text>Antarctica</Text></Value>
			<Value><Code>ATF</Code><Text>French Southern Territories</Text></Value>
			<Value><Code>ATG</Code><Text>Antigua and Barbuda</Text></Value>
			<Value><Code>AUS</Code><Text>Australia</Text></Value>
			<Value><Code>AUT</Code><Text>Austria</Text></Value>
			<Value><Code>AZE</Code><Text>Azerbaijan</Text></Value>
			<Value><Code>BDI</Code><Text>Burundi</Text></Value>
			<Value><Code>BEL</Code><Text>Belgium</Text></Value>
			<Value><Code>BEN</Code><Text>Benin</Text></Value>
			<Value><Code>BES</Code><Text>Bonaire, Sint Eustatius and Saba</Text></Value>
			<Value><Code>BFA</Code><Text>Burkina Faso</Text></Value>
			<Value><Code>BGD</Code><Text>Bangladesh</Text></Value>
			<Value><Code>BGR</Code><Text>Bulgaria</Text></Value>
			<Value><Code>BHR</Code><Text>Bahrain</Text></Value>
			<Value><Code>BHS</Code><Text>Bahamas</Text></Value>
			<Value><Code>BIH</Code><Text>Bosnia and Herzegovina</Text></Value>
			<Value><Code>BLM</Code><Text>Saint Barthélemy</Text></Value>
			<Value><Code>BLR</Code><Text>Belarus</Text></Value>
			<Value><Code>BLZ</Code><Text>Belize</Text></Value>
			<Value><Code>BMU</Code><Text>Bermuda</Text></Value>
			<Value><Code>BOL</Code><Text>Bolivia, Plurinational State of</Text></Value>
			<Value><Code>BRA</Code><Text>Brazil</Text></Value>
			<Value><Code>BRB</Code><Text>Barbados</Text></Value>
			<Value><Code>BRN</Code><Text>Brunei Darussalam</Text></Value>
			<Value><Code>BTN</Code><Text>Bhutan</Text></Value>
			<Value><Code>BVT</Code><Text>Bouvet Island</Text></Value>
			<Value><Code>BWA</Code><Text>Botswana</Text></Value>
			<Value><Code>CAF</Code><Text>Central African Republic</Text></Value>
			<Value><Code>CAN</Code><Text>Canada</Text></Value>
			<Value><Code>CCK</Code><Text>Cocos (Keeling) Islands</Text></Value>
			<Value><Code>CHE</Code><Text>Switzerland</Text></Value>
			<Value><Code>CHL</Code><Text>Chile</Text></Value>
			<Value><Code>CHN</Code><Text>China</Text></Value>
			<Value><Code>CIV</Code><Text>Côte d'Ivoire</Text></Value>
			<Value><Code>CMR</Code><Text>Cameroon</Text></Value>
			<Value><Code>COD</Code><Text>Congo, the Democratic Republic of the</Text></Value>
			<Value><Code>COG</Code><Text>Congo</Text></Value>
			<Value><Code>COK</Code><Text>Cook Islands</Text></Value>
			<Value><Code>COL</Code><Text>Colombia</Text></Value>
			<Value><Code>COM</Code><Text>Comoros</Text></Value>
			<Value><Code>CPV</Code><Text>Cabo Verde</Text></Value>
			<Value><Code>CRI</Code><Text>Costa Rica</Text></Value>
			<Value><Code>CUB</Code><Text>Cuba</Text></Value>
			<Value><Code>CUW</Code><Text>Curaçao</Text></Value>
			<Value><Code>CXR</Code><Text>Christmas Island</Text></Value>
			<Value><Code>CYM</Code><Text>Cayman Islands</Text></Value>
			<Value><Code>CYP</Code><Text>Cyprus</Text></Value>
			<Value><Code>CZE</Code><Text>Czechia</Text></Value>
			<Value><Code>DEU</Code><Text>Germany</Text></Value>
			<Value><Code>DJI</Code><Text>Djibouti</Text></Value>
			<Value><Code>DMA</Code><Text>Dominica</Text></Value>
			<Value><Code>DNK</Code><Text>Denmark</Text></Value>
			<Value><Code>DOM</Code><Text>Dominican Republic</Text></Value>
			<Value><Code>DZA</Code><Text>Algeria</Text></Value>
			<Value><Code>ECU</Code><Text>Ecuador</Text></Value>
			<Value><Code>EGY</Code><Text>Egypt</Text></Value>
			<Value><Code>ERI</Code><Text>Eritrea</Text></Value>
			<Value><Code>ESH</Code><Text>Western Sahara</Text></Value>
			<Value><Code>ESP</Code><Text>Spain</Text></Value>
			<Value><Code>EST</Code><Text>Estonia</Text></Value>
			<Value><Code>ETH</Code><Text>Ethiopia</Text></Value>
			<Value><Code>FIN</Code><Text>Finland</Text></Value>
			<Value><Code>FJI</Code><Text>Fiji</Text></Value>
			<Value><Code>FLK</Code><Text>Falkland Islands (Malvinas)</Text></Value>
			<Value><Code>FRA</Code><Text>France</Text></Value>
			<Value><Code>FRO</Code><Text>Faroe Islands</Text></Value>
			<Value><Code>FSM</Code><Text>Micronesia, Federated States of</Text></Value>
			<Value><Code>GAB</Code><Text>Gabon</Text></Value>
			<Value><Code>GBR</Code><Text>United Kingdom</Text></Value>
			<Value><Code>GEO</Code><Text>Georgia</Text></Value>
			<Value><Code>GGY</Code><Text>Guernsey</Text></Value>
			<Value><Code>GHA</Code><Text>Ghana</Text></Value>
			<Value><Code>GIB</Code><Text>Gibraltar</Text></Value>
			<Value><Code>GIN</Code><Text>Guinea</Text></Value>
			<Value><Code>GLP</Code><Text>Guadeloupe</Text></Value>
			<Value><Code>GMB</Code><Text>Gambia</Text></Value>
			<Value><Code>GNB</Code><Text>Guinea-Bissau</Text></Value>
			<Value><Code>GNQ</Code><Text>Equatorial Guinea</Text></Value>
			<Value><Code>GRC</Code><Text>Greece</Text></Value>
			<Value><Code>GRD</Code><Text>Grenada</Text></Value>
			<Value><Code>GRL</Code><Text>Greenland</Text></Value>
			<Value><Code>GTM</Code><Text>Guatemala</Text></Value>
			<Value><Code>GUF</Code><Text>French Guiana</Text></Value>
			<Value><Code>GUM</Code><Text>Guam</Text></Value>
			<Value><Code>GUY</Code><Text>Guyana</Text></Value>
			<Value><Code>HKG</Code><Text>Hong Kong</Text></Value>
			<Value><Code>HMD</Code><Text>Heard Island and McDonald Islands</Text></Value>
			<Value><Code>HND</Code><Text>Honduras</Text></Value>
			<Value><Code>HRV</Code><Text>Croatia</Text></Value>
			<Value><Code>HTI</Code><Text>Haiti</Text></Value>
			<Value><Code>HUN</Code><Text>Hungary</Text></Value>
			<Value><Code>IDN</Code><Text>Indonesia</Text></Value>
			<Value><Code>IMN</Code><Text>Isle of Man</Text></Value>
			<Value><Code>IND</Code><Text>India</Text></Value>
			<Value><Code>IOT</Code><Text>British Indian Ocean Territory</Text></Value>
			<Value><Code>IRL</Code><Text>Ireland</Text></Value>
			<Value><Code>IRN</Code><Text>Iran, Islamic Republic of</Text></Value>
			<Value><Code>IRQ</Code><Text>Iraq</Text></Value>
			<Value><Code>ISL</Code><Text>Iceland</Text></Value>
			<Value><Code>ISR</Code><Text>Israel</Text></Value>
			<Value><Code>ITA</Code><Text>Italy</Text></Value>
			<Value><Code>JAM</Code><Text>Jamaica</Text></Value>
			<Value><Code>JEY</Code><Text>Jersey</Text></Value>
			<Value><Code>JOR</Code><Text>Jordan</Text></Value>
			<Value><Code>JPN</Code><Text>Japan</Text></Value>
			<Value><Code>KAZ</Code><Text>Kazakhstan</Text></Value>
			<Value><Code>KEN</Code><Text>Kenya</Text></Value>
			<Value><Code>KGZ</Code><Text>Kyrgyzstan</Text></Value>
			<Value><Code>KHM</Code><Text>Cambodia</Text></Value>
			<Value><Code>KIR</Code><Text>Kiribati</Text></Value>
			<Value><Code>KNA</Code><Text>Saint Kitts and Nevis</Text></Value>
			<Value><Code>KOR</Code><Text>Korea, Republic of</Text></Value>
			<Value><Code>KWT</Code><Text>Kuwait</Text></Value>
			<Value><Code>LAO</Code><Text>Lao People's Democratic Republic</Text></Value>
			<Value><Code>LBN</Code><Text>Lebanon</Text></Value>
			<Value><Code>LBR</Code><Text>Liberia</Text></Value>
			<Value><Code>LBY</Code><Text>Libya</Text></Value>
			<Value><Code>LCA</Code><Text>Saint Lucia</Text></Value>
			<Value><Code>LIE</Code><Text>Liechtenstein</Text></Value>
			<Value><Code>LKA</Code><Text>Sri Lanka</Text></Value>
			<Value><Code>LSO</Code><Text>Lesotho</Text></Value>
			<Value><Code>LTU</Code><Text>Lithuania</Text></Value>
			<Value><Code>LUX</Code><Text>Luxembourg</Text></Value>
			<Value><Code>LVA</Code><Text>Latvia</Text></Value>
			<Value><Code>MAC</Code><Text>Macao</Text></Value>
			<Value><Code>MAF</Code><Text>Saint Martin (French part)</Text></Value>
			<Value><Code>MAR</Code><Text>Morocco</Text></Value>
			<Value><Code>MCO</Code><Text>Monaco</Text></Value>
			<Value><Code>MDA</Code><Text>Moldova, Republic of</Text></Value>
			<Value><Code>MDG</Code><Text>Madagascar</Text></Value>
			<Value><Code>MDV</Code><Text>Maldives</Text></Value>
			<Value><Code>MEX</Code><Text>Mexico</Text></Value>
			<Value><Code>MHL</Code><Text>Marshall Islands</Text></Value>
			<Value><Code>MKD</Code><Text>Macedonia, the former Yugoslav Republic of</Text></Value>
			<Value><Code>MLI</Code><Text>Mali</Text></Value>
			<Value><Code>MLT</Code><Text>Malta</Text></Value>
			<Value><Code>MMR</Code><Text>Myanmar</Text></Value>
			<Value><Code>MNE</Code><Text>Montenegro</Text></Value>
			<Value><Code>MNG</Code><Text>Mongolia</Text></Value>
			<Value><Code>MNP</Code><Text>Northern Mariana Islands</Text></Value>
			<Value><Code>MOZ</Code><Text>Mozambique</Text></Value>
			<Value><Code>MRT</Code><Text>Mauritania</Text></Value>
			<Value><Code>MSR</Code><Text>Montserrat</Text></Value>
			<Value><Code>MTQ</Code><Text>Martinique</Text></Value>
			<Value><Code>MUS</Code><Text>Mauritius</Text></Value>
			<Value><Code>MWI</Code><Text>Malawi</Text></Value>
			<Value><Code>MYS</Code><Text>Malaysia</Text></Value>
			<Value><Code>MYT</Code><Text>Mayotte</Text></Value>
			<Value><Code>NAM</Code><Text>Namibia</Text></Value>
			<Value><Code>NCL</Code><Text>New Caledonia</Text></Value>
			<Value><Code>NER</Code><Text>Niger</Text></Value>
			<Value><Code>NFK</Code><Text>Norfolk Island</Text></Value>
			<Value><Code>NGA</Code><Text>Nigeria</Text></Value>
			<Value><Code>NIC</Code><Text>Nicaragua</Text></Value>
			<Value><Code>NIU</Code><Text>Niue</Text></Value>
			<Value><Code>NLD</Code><Text>Netherlands</Text></Value>
			<Value><Code>NOR</Code><Text>Norway</Text></Value>
			<Value><Code>NPL</Code><Text>Nepal</Text></Value>
			<Value><Code>NRU</Code><Text>Nauru</Text></Value>
			<Value><Code>NZL</Code><Text>New Zealand</Text></Value>
			<Value><Code>OMN</Code><Text>Oman</Text></Value>
			<Value><Code>PAK</Code><Text>Pakistan</Text></Value>
			<Value><Code>PAN</Code><Text>Panama</Text></Value>
			<Value><Code>PCN</Code><Text>Pitcairn</Text></Value>
			<Value><Code>PER</Code><Text>Peru</Text></Value>
			<Value><Code>PHL</Code><Text>Philippines</Text></Value>
			<Value><Code>PLW</Code><Text>Palau</Text></Value>
			<Value><Code>PNG</Code><Text>Papua New Guinea</Text></Value>
			<Value><Code>POL</Code><Text>Poland</Text></Value>
			<Value><Code>PRI</Code><Text>Puerto Rico</Text></Value>
			<Value><Code>PRK</Code><Text>Korea, Democratic People's Republic of</Text></Value>
			<Value><Code>PRT</Code><Text>Portugal</Text></Value>
			<Value><Code>PRY</Code><Text>Paraguay</Text></Value>
			<Value><Code>PSE</Code><Text>Palestine, State of</Text></Value>
			<Value><Code>PYF</Code><Text>French Polynesia</Text></Value>
			<Value><Code>QAT</Code><Text>Qatar</Text></Value>
			<Value><Code>REU</Code><Text>Réunion</Text></Value>
			<Value><Code>ROU</Code><Text>Romania</Text></Value>
			<Value><Code>RUS</Code><Text>Russian Federation</Text></Value>
			<Value><Code>RWA</Code><Text>Rwanda</Text></Value>
			<Value><Code>SAU</Code><Text>Saudi Arabia</Text></Value>
			<Value><Code>SDN</Code><Text>Sudan</Text></Value>
			<Value><Code>SEN</Code><Text>Senegal</Text></Value>
			<Value><Code>SGP</Code><Text>Singapore</Text></Value>
			<Value><Code>SGS</Code><Text>South Georgia and the South Sandwich Islands</Text></Value>
			<Value><Code>SHN</Code><Text>Saint Helena, Ascension and Tristan da Cunha</Text></Value>
			<Value><Code>SJM</Code><Text>Svalbard and Jan Mayen</Text></Value>
			<Value><Code>SLB</Code><Text>Solomon Islands</Text></Value>
			<Value><Code>SLE</Code><Text>Sierra Leone</Text></Value>
			<Value><Code>SLV</Code><Text>El Salvador</Text></Value>
			<Value><Code>SMR</Code><Text>San Marino</Text></Value>
			<Value><Code>SOM</Code><Text>Somalia</Text></Value>
			<Value><Code>SPM</Code><Text>Saint Pierre and Miquelon</Text></Value>
			<Value><Code>SRB</Code><Text>Serbia</Text></Value>
			<Value><Code>SSD</Code><Text>South Sudan</Text></Value>
			<Value><Code>STP</Code><Text>Sao Tome and Principe</Text></Value>
			<Value><Code>SUR</Code><Text>Suriname</Text></Value>
			<Value><Code>SVK</Code><Text>Slovakia</Text></Value>
			<Value><Code>SVN</Code><Text>Slovenia</Text></Value>
			<Value><Code>SWE</Code><Text>Sweden</Text></Value>
			<Value><Code>SWZ</Code><Text>Swaziland</Text></Value>
			<Value><Code>SXM</Code><Text>Sint Maarten (Dutch part)</Text></Value>
			<Value><Code>SYC</Code><Text>Seychelles</Text></Value>
			<Value><Code>SYR</Code><Text>Syrian Arab Republic</Text></Value>
			<Value><Code>TCA</Code><Text>Turks and Caicos Islands</Text></Value>
			<Value><Code>TCD</Code><Text>Chad</Text></Value>
			<Value><Code>TGO</Code><Text>Togo</Text></Value>
			<Value><Code>THA</Code><Text>Thailand</Text></Value>
			<Value><Code>TJK</Code><Text>Tajikistan</Text></Value>
			<Value><Code>TKL</Code><Text>Tokelau</Text></Value>
			<Value><Code>TKM</Code><Text>Turkmenistan</Text></Value>
			<Value><Code>TLS</Code><Text>Timor-Leste</Text></Value>
			<Value><Code>TON</Code><Text>Tonga</Text></Value>
			<Value><Code>TTO</Code><Text>Trinidad and Tobago</Text></Value>
			<Value><Code>TUN</Code><Text>Tunisia</Text></Value>
			<Value><Code>TUR</Code><Text>Turkey</Text></Value>
			<Value><Code>TUV</Code><Text>Tuvalu</Text></Value>
			<Value><Code>TWN</Code><Text>Taiwan, Province of China</Text></Value>
			<Value><Code>TZA</Code><Text>Tanzania, United Republic of</Text></Value>
			<Value><Code>UGA</Code><Text>Uganda</Text></Value>
			<Value><Code>UKR</Code><Text>Ukraine</Text></Value>
			<Value><Code>UMI</Code><Text>United States Minor Outlying Islands</Text></Value>
			<Value><Code>URY</Code><Text>Uruguay</Text></Value>
			<Value><Code>USA</Code><Text>United States of America</Text></Value>
			<Value><Code>UZB</Code><Text>Uzbekistan</Text></Value>
			<Value><Code>VAT</Code><Text>Holy See</Text></Value>
			<Value><Code>VCT</Code><Text>Saint Vincent and the Grenadines</Text></Value>
			<Value><Code>VEN</Code><Text>Venezuela, Bolivarian Republic of</Text></Value>
			<Value><Code>VGB</Code><Text>Virgin Islands, British</Text></Value>
			<Value><Code>VIR</Code><Text>Virgin Islands, U.S.</Text></Value>
			<Value><Code>VNM</Code><Text>Viet Nam</Text></Value>
			<Value><Code>VUT</Code><Text>Vanuatu</Text></Value>
			<Value><Code>WLF</Code><Text>Wallis and Futuna</Text></Value>
			<Value><Code>WSM</Code><Text>Samoa</Text></Value>
			<Value><Code>YEM</Code><Text>Yemen</Text></Value>
			<Value><Code>ZAF</Code><Text>South Africa</Text></Value>
			<Value><Code>ZMB</Code><Text>Zambia</Text></Value>
			<Value><Code>ZWE</Code><Text>Zimbabwe</Text></Value>
		</Values>
	</CodeSet>   <!-- ISO 3166 - International Country Codes -->
</Grouping>
</CodeSets>
</Appendix>
